{
  "id": "silver",
  "range": "2Y",
  "points": [
    {
      "label": "07/22 21:54",
      "value": 60.393
    },
    {
      "label": "07/22 21:56",
      "value": 60.385
    },
    {
      "label": "07/22 21:58",
      "value": 60.539
    },
    {
      "label": "07/22 22:02",
      "value": 60.792
    },
    {
      "label": "07/22 22:04",
      "value": 60.917
    },
    {
      "label": "07/22 22:06",
      "value": 60.816
    },
    {
      "label": "07/22 22:08",
      "value": 60.867
    },
    {
      "label": "07/22 22:12",
      "value": 60.857
    },
    {
      "label": "07/22 22:14",
      "value": 60.825
    },
    {
      "label": "07/22 22:16",
      "value": 60.797
    },
    {
      "label": "07/22 22:18",
      "value": 60.605
    },
    {
      "label": "07/22 22:20",
      "value": 60.518
    },
    {
      "label": "07/22 22:22",
      "value": 60.589
    },
    {
      "label": "07/22 22:24",
      "value": 60.473
    },
    {
      "label": "07/22 22:26",
      "value": 60.464
    },
    {
      "label": "07/22 22:28",
      "value": 60.328
    },
    {
      "label": "07/22 22:32",
      "value": 60.452
    },
    {
      "label": "07/22 22:35",
      "value": 60.416
    },
    {
      "label": "07/22 22:36",
      "value": 60.432
    },
    {
      "label": "07/22 22:38",
      "value": 60.469
    },
    {
      "label": "07/22 22:42",
      "value": 60.293
    },
    {
      "label": "07/22 22:44",
      "value": 60.434
    },
    {
      "label": "07/22 22:46",
      "value": 60.462
    },
    {
      "label": "07/22 22:48",
      "value": 60.313
    },
    {
      "label": "07/22 22:50",
      "value": 60.378
    },
    {
      "label": "07/22 22:52",
      "value": 60.314
    },
    {
      "label": "07/22 22:54",
      "value": 60.326
    },
    {
      "label": "07/22 22:56",
      "value": 60.275
    },
    {
      "label": "07/22 22:58",
      "value": 60.349
    },
    {
      "label": "07/22 23:02",
      "value": 60.36
    },
    {
      "label": "07/22 23:04",
      "value": 60.412
    },
    {
      "label": "07/22 23:06",
      "value": 60.454
    },
    {
      "label": "07/22 23:08",
      "value": 60.45
    },
    {
      "label": "07/22 23:11",
      "value": 60.436
    },
    {
      "label": "07/22 23:13",
      "value": 60.482
    },
    {
      "label": "07/22 23:14",
      "value": 60.468
    },
    {
      "label": "07/22 23:16",
      "value": 60.39
    },
    {
      "label": "07/22 23:18",
      "value": 60.339
    },
    {
      "label": "07/22 23:22",
      "value": 60.378
    },
    {
      "label": "07/22 23:24",
      "value": 60.534
    },
    {
      "label": "07/22 23:26",
      "value": 60.524
    },
    {
      "label": "07/22 23:28",
      "value": 60.487
    },
    {
      "label": "07/22 23:32",
      "value": 60.411
    },
    {
      "label": "07/22 23:34",
      "value": 60.368
    },
    {
      "label": "07/22 23:36",
      "value": 60.335
    },
    {
      "label": "07/22 23:38",
      "value": 60.354
    },
    {
      "label": "07/22 23:42",
      "value": 60.376
    },
    {
      "label": "07/22 23:43",
      "value": 60.405
    },
    {
      "label": "07/22 23:46",
      "value": 60.394
    },
    {
      "label": "07/22 23:48",
      "value": 60.379
    },
    {
      "label": "07/22 23:52",
      "value": 60.478
    },
    {
      "label": "07/22 23:53",
      "value": 60.474
    },
    {
      "label": "07/22 23:56",
      "value": 60.382
    },
    {
      "label": "07/22 23:58",
      "value": 60.35
    },
    {
      "label": "07/23 00:02",
      "value": 60.357
    },
    {
      "label": "07/23 00:04",
      "value": 60.364
    },
    {
      "label": "07/23 00:06",
      "value": 60.384
    },
    {
      "label": "07/23 00:08",
      "value": 60.387
    },
    {
      "label": "07/23 00:10",
      "value": 60.363
    },
    {
      "label": "07/23 00:12",
      "value": 60.262
    },
    {
      "label": "07/23 00:14",
      "value": 60.232
    },
    {
      "label": "07/23 00:16",
      "value": 60.228
    },
    {
      "label": "07/23 00:18",
      "value": 60.254
    },
    {
      "label": "07/23 00:22",
      "value": 60.282
    },
    {
      "label": "07/23 00:25",
      "value": 60.24
    },
    {
      "label": "07/23 00:26",
      "value": 60.204
    },
    {
      "label": "07/23 00:28",
      "value": 60.212
    },
    {
      "label": "07/23 00:32",
      "value": 60.257
    },
    {
      "label": "07/23 00:34",
      "value": 60.244
    },
    {
      "label": "07/23 00:36",
      "value": 60.234
    },
    {
      "label": "07/23 00:37",
      "value": 60.222
    },
    {
      "label": "07/23 00:38",
      "value": 60.217
    },
    {
      "label": "07/23 00:42",
      "value": 60.217
    },
    {
      "label": "07/23 00:44",
      "value": 60.181
    },
    {
      "label": "07/23 00:46",
      "value": 60.107
    },
    {
      "label": "07/23 00:49",
      "value": 60.138
    },
    {
      "label": "07/23 00:54",
      "value": 60.072
    },
    {
      "label": "07/23 00:56",
      "value": 60.092
    },
    {
      "label": "07/23 00:58",
      "value": 60.188
    },
    {
      "label": "07/23 01:02",
      "value": 60.146
    },
    {
      "label": "07/23 01:04",
      "value": 60.093
    },
    {
      "label": "07/23 01:06",
      "value": 60.099
    },
    {
      "label": "07/23 01:08",
      "value": 60.09
    },
    {
      "label": "07/23 01:12",
      "value": 60.041
    },
    {
      "label": "07/23 01:14",
      "value": 60.03
    },
    {
      "label": "07/23 01:16",
      "value": 60.001
    },
    {
      "label": "07/23 01:18",
      "value": 60.027
    },
    {
      "label": "07/23 01:20",
      "value": 59.96
    },
    {
      "label": "07/23 01:22",
      "value": 60.009
    },
    {
      "label": "07/23 01:24",
      "value": 60.101
    },
    {
      "label": "07/23 01:26",
      "value": 60.06
    },
    {
      "label": "07/23 01:28",
      "value": 60.075
    },
    {
      "label": "07/23 01:32",
      "value": 60.101
    },
    {
      "label": "07/23 01:34",
      "value": 60.14
    },
    {
      "label": "07/23 01:36",
      "value": 60.093
    },
    {
      "label": "07/23 01:38",
      "value": 60.011
    },
    {
      "label": "07/23 01:40",
      "value": 59.925
    },
    {
      "label": "07/23 01:42",
      "value": 59.972
    },
    {
      "label": "07/23 01:44",
      "value": 60.036
    },
    {
      "label": "07/23 01:46",
      "value": 60.033
    },
    {
      "label": "07/23 01:48",
      "value": 60.066
    },
    {
      "label": "07/23 01:51",
      "value": 60.164
    },
    {
      "label": "07/23 01:52",
      "value": 60.162
    },
    {
      "label": "07/23 01:54",
      "value": 60.139
    },
    {
      "label": "07/23 01:56",
      "value": 60.111
    },
    {
      "label": "07/23 01:58",
      "value": 60.124
    },
    {
      "label": "07/23 02:02",
      "value": 59.972
    },
    {
      "label": "07/23 02:04",
      "value": 60.015
    },
    {
      "label": "07/23 02:06",
      "value": 60.048
    },
    {
      "label": "07/23 02:08",
      "value": 60.1
    },
    {
      "label": "07/23 02:10",
      "value": 60.067
    },
    {
      "label": "07/23 02:12",
      "value": 60.049
    },
    {
      "label": "07/23 02:14",
      "value": 60.049
    },
    {
      "label": "07/23 02:16",
      "value": 60.041
    },
    {
      "label": "07/23 02:18",
      "value": 60.026
    },
    {
      "label": "07/23 02:20",
      "value": 60.026
    },
    {
      "label": "07/23 02:22",
      "value": 59.983
    },
    {
      "label": "07/23 02:25",
      "value": 59.983
    },
    {
      "label": "07/23 02:26",
      "value": 59.999
    },
    {
      "label": "07/23 02:28",
      "value": 60.016
    },
    {
      "label": "07/23 02:32",
      "value": 59.963
    },
    {
      "label": "07/23 02:34",
      "value": 59.985
    },
    {
      "label": "07/23 02:36",
      "value": 59.959
    },
    {
      "label": "07/23 02:38",
      "value": 59.96
    },
    {
      "label": "07/23 02:42",
      "value": 59.943
    },
    {
      "label": "07/23 02:43",
      "value": 59.931
    },
    {
      "label": "07/23 02:44",
      "value": 59.958
    },
    {
      "label": "07/23 02:46",
      "value": 59.999
    },
    {
      "label": "07/23 02:48",
      "value": 60.046
    },
    {
      "label": "07/23 02:51",
      "value": 60.052
    },
    {
      "label": "07/23 02:54",
      "value": 60.048
    },
    {
      "label": "07/23 02:56",
      "value": 60.057
    },
    {
      "label": "07/23 02:58",
      "value": 60.045
    },
    {
      "label": "07/23 03:02",
      "value": 59.939
    },
    {
      "label": "07/23 03:04",
      "value": 59.935
    },
    {
      "label": "07/23 03:06",
      "value": 59.998
    },
    {
      "label": "07/23 03:08",
      "value": 60.004
    },
    {
      "label": "07/23 03:12",
      "value": 59.967
    },
    {
      "label": "07/23 03:14",
      "value": 59.977
    },
    {
      "label": "07/23 03:17",
      "value": 59.964
    },
    {
      "label": "07/23 03:18",
      "value": 59.946
    },
    {
      "label": "07/23 03:22",
      "value": 59.893
    },
    {
      "label": "07/23 03:24",
      "value": 59.953
    },
    {
      "label": "07/23 03:26",
      "value": 59.941
    },
    {
      "label": "07/23 03:28",
      "value": 59.944
    },
    {
      "label": "07/23 03:32",
      "value": 59.975
    },
    {
      "label": "07/23 03:34",
      "value": 60.025
    },
    {
      "label": "07/23 03:36",
      "value": 60.014
    },
    {
      "label": "07/23 03:38",
      "value": 59.946
    },
    {
      "label": "07/23 03:41",
      "value": 59.946
    },
    {
      "label": "07/23 03:42",
      "value": 59.95
    },
    {
      "label": "07/23 03:44",
      "value": 59.96
    },
    {
      "label": "07/23 03:47",
      "value": 59.832
    },
    {
      "label": "07/23 03:49",
      "value": 59.877
    },
    {
      "label": "07/23 03:50",
      "value": 59.878
    },
    {
      "label": "07/23 03:52",
      "value": 59.827
    },
    {
      "label": "07/23 03:54",
      "value": 59.744
    },
    {
      "label": "07/23 03:56",
      "value": 59.715
    },
    {
      "label": "07/23 03:58",
      "value": 59.772
    },
    {
      "label": "07/23 04:02",
      "value": 59.867
    },
    {
      "label": "07/23 04:04",
      "value": 59.784
    },
    {
      "label": "07/23 04:06",
      "value": 59.772
    },
    {
      "label": "07/23 04:08",
      "value": 59.762
    },
    {
      "label": "07/23 04:10",
      "value": 59.75
    },
    {
      "label": "07/23 04:12",
      "value": 59.747
    },
    {
      "label": "07/23 04:14",
      "value": 59.771
    },
    {
      "label": "07/23 04:16",
      "value": 59.828
    },
    {
      "label": "07/23 04:19",
      "value": 59.968
    },
    {
      "label": "07/23 04:20",
      "value": 59.968
    },
    {
      "label": "07/23 04:23",
      "value": 59.969
    },
    {
      "label": "07/23 04:24",
      "value": 59.999
    },
    {
      "label": "07/23 04:26",
      "value": 60.022
    },
    {
      "label": "07/23 04:28",
      "value": 60.007
    },
    {
      "label": "07/23 04:32",
      "value": 59.982
    },
    {
      "label": "07/23 04:34",
      "value": 59.964
    },
    {
      "label": "07/23 04:36",
      "value": 59.898
    },
    {
      "label": "07/23 04:38",
      "value": 59.908
    },
    {
      "label": "07/23 04:40",
      "value": 59.906
    },
    {
      "label": "07/23 04:42",
      "value": 59.911
    },
    {
      "label": "07/23 04:44",
      "value": 59.851
    },
    {
      "label": "07/23 04:46",
      "value": 59.853
    },
    {
      "label": "07/23 04:48",
      "value": 59.831
    },
    {
      "label": "07/23 04:52",
      "value": 59.752
    },
    {
      "label": "07/23 04:54",
      "value": 59.854
    },
    {
      "label": "07/23 04:56",
      "value": 59.829
    },
    {
      "label": "07/23 04:58",
      "value": 59.824
    },
    {
      "label": "07/23 05:02",
      "value": 59.839
    },
    {
      "label": "07/23 05:03",
      "value": 59.839
    },
    {
      "label": "07/23 05:07",
      "value": 59.839
    },
    {
      "label": "07/23 05:08",
      "value": 59.839
    },
    {
      "label": "07/23 05:10",
      "value": 59.839
    },
    {
      "label": "07/23 05:12",
      "value": 59.839
    },
    {
      "label": "07/23 05:14",
      "value": 59.839
    },
    {
      "label": "07/23 05:16",
      "value": 59.839
    },
    {
      "label": "07/23 05:18",
      "value": 59.839
    },
    {
      "label": "07/23 05:22",
      "value": 59.839
    },
    {
      "label": "07/23 05:24",
      "value": 59.839
    },
    {
      "label": "07/23 05:26",
      "value": 59.839
    },
    {
      "label": "07/23 05:28",
      "value": 59.839
    },
    {
      "label": "07/23 05:32",
      "value": 59.839
    },
    {
      "label": "07/23 05:34",
      "value": 59.839
    },
    {
      "label": "07/23 05:36",
      "value": 59.839
    },
    {
      "label": "07/23 05:38",
      "value": 59.839
    },
    {
      "label": "07/23 05:38",
      "value": 59.839
    },
    {
      "label": "07/23 05:42",
      "value": 59.839
    },
    {
      "label": "07/23 05:44",
      "value": 59.839
    },
    {
      "label": "07/23 05:46",
      "value": 59.839
    },
    {
      "label": "07/23 05:48",
      "value": 59.839
    },
    {
      "label": "07/23 05:52",
      "value": 59.839
    },
    {
      "label": "07/23 05:53",
      "value": 59.839
    },
    {
      "label": "07/23 05:54",
      "value": 59.839
    },
    {
      "label": "07/23 05:56",
      "value": 59.839
    },
    {
      "label": "07/23 05:58",
      "value": 59.839
    },
    {
      "label": "07/23 06:02",
      "value": 59.791
    },
    {
      "label": "07/23 06:04",
      "value": 59.719
    },
    {
      "label": "07/23 06:05",
      "value": 59.72
    },
    {
      "label": "07/23 06:08",
      "value": 59.703
    },
    {
      "label": "07/23 06:10",
      "value": 59.696
    },
    {
      "label": "07/23 06:13",
      "value": 59.663
    },
    {
      "label": "07/23 06:14",
      "value": 59.68
    },
    {
      "label": "07/23 06:16",
      "value": 59.701
    },
    {
      "label": "07/23 06:18",
      "value": 59.652
    },
    {
      "label": "07/23 06:21",
      "value": 59.734
    },
    {
      "label": "07/23 06:24",
      "value": 59.713
    },
    {
      "label": "07/23 06:26",
      "value": 59.711
    },
    {
      "label": "07/23 06:28",
      "value": 59.746
    },
    {
      "label": "07/23 06:32",
      "value": 59.711
    },
    {
      "label": "07/23 06:34",
      "value": 59.665
    },
    {
      "label": "07/23 06:37",
      "value": 59.612
    },
    {
      "label": "07/23 06:38",
      "value": 59.604
    },
    {
      "label": "07/23 06:41",
      "value": 59.502
    },
    {
      "label": "07/23 06:42",
      "value": 59.507
    },
    {
      "label": "07/23 06:44",
      "value": 59.494
    },
    {
      "label": "07/23 06:46",
      "value": 59.473
    },
    {
      "label": "07/23 06:48",
      "value": 59.499
    },
    {
      "label": "07/23 06:52",
      "value": 59.493
    },
    {
      "label": "07/23 06:54",
      "value": 59.481
    },
    {
      "label": "07/23 06:56",
      "value": 59.466
    },
    {
      "label": "07/23 06:58",
      "value": 59.515
    },
    {
      "label": "07/23 07:02",
      "value": 59.492
    },
    {
      "label": "07/23 07:04",
      "value": 59.484
    },
    {
      "label": "07/23 07:06",
      "value": 59.476
    },
    {
      "label": "07/23 07:08",
      "value": 59.499
    },
    {
      "label": "07/23 07:12",
      "value": 59.506
    },
    {
      "label": "07/23 07:13",
      "value": 59.523
    },
    {
      "label": "07/23 07:16",
      "value": 59.563
    },
    {
      "label": "07/23 07:18",
      "value": 59.568
    },
    {
      "label": "07/23 07:21",
      "value": 59.576
    },
    {
      "label": "07/23 07:24",
      "value": 59.603
    },
    {
      "label": "07/23 07:26",
      "value": 59.601
    },
    {
      "label": "07/23 07:28",
      "value": 59.602
    },
    {
      "label": "07/23 07:32",
      "value": 59.597
    },
    {
      "label": "07/23 07:34",
      "value": 59.659
    },
    {
      "label": "07/23 07:35",
      "value": 59.649
    },
    {
      "label": "07/23 07:36",
      "value": 59.637
    },
    {
      "label": "07/23 07:38",
      "value": 59.686
    },
    {
      "label": "07/23 07:42",
      "value": 59.673
    },
    {
      "label": "07/23 07:44",
      "value": 59.728
    },
    {
      "label": "07/23 07:46",
      "value": 59.75
    },
    {
      "label": "07/23 07:48",
      "value": 59.771
    },
    {
      "label": "07/23 07:52",
      "value": 59.793
    },
    {
      "label": "07/23 07:54",
      "value": 59.777
    },
    {
      "label": "07/23 07:56",
      "value": 59.806
    },
    {
      "label": "07/23 07:58",
      "value": 59.826
    },
    {
      "label": "07/23 08:02",
      "value": 59.826
    },
    {
      "label": "07/23 08:04",
      "value": 59.768
    },
    {
      "label": "07/23 08:07",
      "value": 59.839
    },
    {
      "label": "07/23 08:08",
      "value": 59.835
    },
    {
      "label": "07/23 08:10",
      "value": 59.832
    },
    {
      "label": "07/23 08:12",
      "value": 59.826
    },
    {
      "label": "07/23 08:14",
      "value": 59.759
    },
    {
      "label": "07/23 08:16",
      "value": 59.811
    },
    {
      "label": "07/23 08:18",
      "value": 59.832
    },
    {
      "label": "07/23 08:22",
      "value": 59.815
    },
    {
      "label": "07/23 08:23",
      "value": 59.878
    },
    {
      "label": "07/23 08:24",
      "value": 59.878
    },
    {
      "label": "07/23 08:26",
      "value": 59.93
    },
    {
      "label": "07/23 08:28",
      "value": 59.985
    },
    {
      "label": "07/23 08:31",
      "value": 59.876
    },
    {
      "label": "07/23 08:34",
      "value": 59.909
    },
    {
      "label": "07/23 08:36",
      "value": 59.924
    },
    {
      "label": "07/23 08:38",
      "value": 59.917
    },
    {
      "label": "07/23 08:41",
      "value": 59.86
    },
    {
      "label": "07/23 08:42",
      "value": 59.883
    },
    {
      "label": "07/23 08:44",
      "value": 59.838
    },
    {
      "label": "07/23 08:46",
      "value": 59.918
    },
    {
      "label": "07/23 08:48",
      "value": 59.869
    },
    {
      "label": "07/23 08:52",
      "value": 59.832
    },
    {
      "label": "07/23 08:53",
      "value": 59.846
    },
    {
      "label": "07/23 08:54",
      "value": 59.893
    },
    {
      "label": "07/23 08:56",
      "value": 59.899
    },
    {
      "label": "07/23 08:58",
      "value": 59.907
    },
    {
      "label": "07/23 09:01",
      "value": 60.127
    },
    {
      "label": "07/23 09:02",
      "value": 60.173
    },
    {
      "label": "07/23 09:04",
      "value": 59.899
    },
    {
      "label": "07/23 09:06",
      "value": 59.915
    },
    {
      "label": "07/23 09:08",
      "value": 59.835
    },
    {
      "label": "07/23 09:12",
      "value": 59.948
    },
    {
      "label": "07/23 09:14",
      "value": 59.987
    },
    {
      "label": "07/23 09:16",
      "value": 60.033
    },
    {
      "label": "07/23 09:18",
      "value": 60.075
    },
    {
      "label": "07/23 09:20",
      "value": 60.05
    },
    {
      "label": "07/23 09:22",
      "value": 60.11
    },
    {
      "label": "07/23 09:24",
      "value": 60.129
    },
    {
      "label": "07/23 09:26",
      "value": 60.114
    },
    {
      "label": "07/23 09:28",
      "value": 60.121
    },
    {
      "label": "07/23 09:32",
      "value": 59.788
    },
    {
      "label": "07/23 09:34",
      "value": 59.935
    },
    {
      "label": "07/23 09:36",
      "value": 59.844
    },
    {
      "label": "07/23 09:37",
      "value": 59.759
    },
    {
      "label": "07/23 09:42",
      "value": 59.757
    },
    {
      "label": "07/23 09:44",
      "value": 59.725
    },
    {
      "label": "07/23 09:46",
      "value": 59.734
    },
    {
      "label": "07/23 09:48",
      "value": 59.646
    },
    {
      "label": "07/23 09:52",
      "value": 59.737
    },
    {
      "label": "07/23 09:54",
      "value": 59.659
    },
    {
      "label": "07/23 09:56",
      "value": 59.663
    },
    {
      "label": "07/23 09:58",
      "value": 59.587
    },
    {
      "label": "07/23 10:01",
      "value": 59.655
    },
    {
      "label": "07/23 10:02",
      "value": 59.696
    },
    {
      "label": "07/23 10:04",
      "value": 59.624
    },
    {
      "label": "07/23 10:06",
      "value": 59.672
    },
    {
      "label": "07/23 10:08",
      "value": 59.75
    },
    {
      "label": "07/23 10:12",
      "value": 59.665
    },
    {
      "label": "07/23 10:14",
      "value": 59.727
    },
    {
      "label": "07/23 10:16",
      "value": 59.658
    },
    {
      "label": "07/23 10:18",
      "value": 59.627
    },
    {
      "label": "07/23 10:21",
      "value": 59.572
    },
    {
      "label": "07/23 10:22",
      "value": 59.606
    },
    {
      "label": "07/23 10:24",
      "value": 59.58
    },
    {
      "label": "07/23 10:26",
      "value": 59.596
    },
    {
      "label": "07/23 10:28",
      "value": 59.575
    },
    {
      "label": "07/23 10:32",
      "value": 59.724
    },
    {
      "label": "07/23 10:34",
      "value": 59.681
    },
    {
      "label": "07/23 10:36",
      "value": 59.64
    },
    {
      "label": "07/23 10:38",
      "value": 59.645
    },
    {
      "label": "07/23 10:40",
      "value": 59.702
    },
    {
      "label": "07/23 10:42",
      "value": 59.709
    },
    {
      "label": "07/23 10:44",
      "value": 59.723
    },
    {
      "label": "07/23 10:47",
      "value": 59.89
    },
    {
      "label": "07/23 10:48",
      "value": 59.876
    },
    {
      "label": "07/23 10:52",
      "value": 59.904
    },
    {
      "label": "07/23 10:53",
      "value": 59.882
    },
    {
      "label": "07/23 10:54",
      "value": 59.89
    },
    {
      "label": "07/23 10:56",
      "value": 59.905
    },
    {
      "label": "07/23 10:58",
      "value": 59.957
    },
    {
      "label": "07/23 11:02",
      "value": 59.97
    },
    {
      "label": "07/23 11:03",
      "value": 59.978
    },
    {
      "label": "07/23 11:04",
      "value": 59.93
    },
    {
      "label": "07/23 11:06",
      "value": 59.863
    },
    {
      "label": "07/23 11:08",
      "value": 59.894
    },
    {
      "label": "07/23 11:12",
      "value": 59.884
    },
    {
      "label": "07/23 11:13",
      "value": 59.884
    },
    {
      "label": "07/23 11:14",
      "value": 59.871
    },
    {
      "label": "07/23 11:16",
      "value": 59.875
    },
    {
      "label": "07/23 11:18",
      "value": 59.968
    },
    {
      "label": "07/23 11:21",
      "value": 59.99
    },
    {
      "label": "07/23 11:24",
      "value": 60.02
    },
    {
      "label": "07/23 11:26",
      "value": 60
    },
    {
      "label": "07/23 11:28",
      "value": 59.95
    },
    {
      "label": "07/23 11:32",
      "value": 59.96
    },
    {
      "label": "07/23 11:34",
      "value": 59.973
    },
    {
      "label": "07/23 11:36",
      "value": 60.006
    },
    {
      "label": "07/23 11:38",
      "value": 59.979
    },
    {
      "label": "07/23 11:42",
      "value": 59.976
    },
    {
      "label": "07/23 11:44",
      "value": 59.947
    },
    {
      "label": "07/23 11:46",
      "value": 59.932
    },
    {
      "label": "07/23 11:48",
      "value": 59.884
    },
    {
      "label": "07/23 11:50",
      "value": 59.875
    },
    {
      "label": "07/23 11:52",
      "value": 59.872
    },
    {
      "label": "07/23 11:54",
      "value": 59.895
    },
    {
      "label": "07/23 11:56",
      "value": 59.884
    },
    {
      "label": "07/23 11:58",
      "value": 59.894
    },
    {
      "label": "07/23 12:02",
      "value": 59.88
    },
    {
      "label": "07/23 12:04",
      "value": 59.845
    },
    {
      "label": "07/23 12:05",
      "value": 59.864
    },
    {
      "label": "07/23 12:08",
      "value": 59.858
    },
    {
      "label": "07/23 12:12",
      "value": 59.89
    },
    {
      "label": "07/23 12:13",
      "value": 59.946
    },
    {
      "label": "07/23 12:16",
      "value": 59.988
    },
    {
      "label": "07/23 12:18",
      "value": 59.956
    },
    {
      "label": "07/23 12:21",
      "value": 59.945
    },
    {
      "label": "07/23 12:22",
      "value": 59.961
    },
    {
      "label": "07/23 12:24",
      "value": 60.027
    },
    {
      "label": "07/23 12:26",
      "value": 60.036
    },
    {
      "label": "07/23 12:28",
      "value": 60.03
    },
    {
      "label": "07/23 12:31",
      "value": 59.985
    },
    {
      "label": "07/23 12:32",
      "value": 59.923
    },
    {
      "label": "07/23 12:34",
      "value": 59.934
    },
    {
      "label": "07/23 12:36",
      "value": 59.939
    },
    {
      "label": "07/23 12:38",
      "value": 59.952
    },
    {
      "label": "07/23 12:42",
      "value": 59.848
    },
    {
      "label": "07/23 12:43",
      "value": 59.85
    },
    {
      "label": "07/23 12:46",
      "value": 59.847
    },
    {
      "label": "07/23 12:48",
      "value": 59.851
    },
    {
      "label": "07/23 12:51",
      "value": 59.774
    },
    {
      "label": "07/23 12:52",
      "value": 59.77
    },
    {
      "label": "07/23 12:54",
      "value": 59.741
    },
    {
      "label": "07/23 12:56",
      "value": 59.739
    },
    {
      "label": "07/23 12:58",
      "value": 59.746
    },
    {
      "label": "07/23 13:02",
      "value": 59.738
    },
    {
      "label": "07/23 13:04",
      "value": 59.719
    },
    {
      "label": "07/23 13:06",
      "value": 59.735
    },
    {
      "label": "07/23 13:08",
      "value": 59.774
    },
    {
      "label": "07/23 13:12",
      "value": 59.779
    },
    {
      "label": "07/23 13:14",
      "value": 59.833
    },
    {
      "label": "07/23 13:16",
      "value": 59.809
    },
    {
      "label": "07/23 13:18",
      "value": 59.758
    },
    {
      "label": "07/23 13:22",
      "value": 59.747
    },
    {
      "label": "07/23 13:24",
      "value": 59.706
    },
    {
      "label": "07/23 13:26",
      "value": 59.733
    },
    {
      "label": "07/23 13:28",
      "value": 59.805
    },
    {
      "label": "07/23 13:31",
      "value": 59.873
    },
    {
      "label": "07/23 13:32",
      "value": 60.01
    },
    {
      "label": "07/23 13:34",
      "value": 59.953
    },
    {
      "label": "07/23 13:36",
      "value": 59.951
    },
    {
      "label": "07/23 13:38",
      "value": 59.972
    },
    {
      "label": "07/23 13:40",
      "value": 59.911
    },
    {
      "label": "07/23 13:42",
      "value": 59.901
    },
    {
      "label": "07/23 13:44",
      "value": 59.817
    },
    {
      "label": "07/23 13:46",
      "value": 59.878
    },
    {
      "label": "07/23 13:48",
      "value": 59.941
    },
    {
      "label": "07/23 13:51",
      "value": 59.776
    },
    {
      "label": "07/23 13:52",
      "value": 59.817
    },
    {
      "label": "07/23 13:54",
      "value": 59.86
    },
    {
      "label": "07/23 13:56",
      "value": 59.735
    },
    {
      "label": "07/23 13:58",
      "value": 59.694
    },
    {
      "label": "07/23 14:02",
      "value": 59.811
    },
    {
      "label": "07/23 14:04",
      "value": 59.777
    },
    {
      "label": "07/23 14:06",
      "value": 59.743
    },
    {
      "label": "07/23 14:08",
      "value": 59.72
    },
    {
      "label": "07/23 14:12",
      "value": 59.743
    },
    {
      "label": "07/23 14:14",
      "value": 59.712
    },
    {
      "label": "07/23 14:16",
      "value": 59.678
    },
    {
      "label": "07/23 14:18",
      "value": 59.731
    },
    {
      "label": "07/23 14:22",
      "value": 59.725
    },
    {
      "label": "07/23 14:24",
      "value": 59.67
    },
    {
      "label": "07/23 14:26",
      "value": 59.655
    },
    {
      "label": "07/23 14:28",
      "value": 59.661
    },
    {
      "label": "07/23 14:31",
      "value": 59.667
    },
    {
      "label": "07/23 14:34",
      "value": 59.624
    },
    {
      "label": "07/23 14:36",
      "value": 59.64
    },
    {
      "label": "07/23 14:38",
      "value": 59.644
    },
    {
      "label": "07/23 14:42",
      "value": 59.579
    },
    {
      "label": "07/23 14:44",
      "value": 59.71
    },
    {
      "label": "07/23 14:46",
      "value": 59.722
    },
    {
      "label": "07/23 14:48",
      "value": 59.72
    },
    {
      "label": "07/23 14:51",
      "value": 59.732
    },
    {
      "label": "07/23 14:52",
      "value": 59.732
    },
    {
      "label": "07/23 14:54",
      "value": 59.657
    },
    {
      "label": "07/23 14:56",
      "value": 59.616
    },
    {
      "label": "07/23 14:58",
      "value": 59.566
    },
    {
      "label": "07/23 15:02",
      "value": 59.509
    },
    {
      "label": "07/23 15:04",
      "value": 59.421
    },
    {
      "label": "07/23 15:05",
      "value": 59.425
    },
    {
      "label": "07/23 15:06",
      "value": 59.409
    },
    {
      "label": "07/23 15:08",
      "value": 59.343
    },
    {
      "label": "07/23 15:12",
      "value": 59.13
    },
    {
      "label": "07/23 15:12",
      "value": 59.055
    },
    {
      "label": "07/23 15:14",
      "value": 59.012
    },
    {
      "label": "07/23 15:16",
      "value": 59.178
    },
    {
      "label": "07/23 15:18",
      "value": 59.245
    },
    {
      "label": "07/23 15:20",
      "value": 59.234
    },
    {
      "label": "07/23 15:22",
      "value": 59.192
    },
    {
      "label": "07/23 15:24",
      "value": 59.208
    },
    {
      "label": "07/23 15:26",
      "value": 59.146
    },
    {
      "label": "07/23 15:28",
      "value": 59.289
    },
    {
      "label": "07/23 15:32",
      "value": 59.132
    },
    {
      "label": "07/23 15:33",
      "value": 59.107
    },
    {
      "label": "07/23 15:34",
      "value": 59.153
    },
    {
      "label": "07/23 15:36",
      "value": 59.083
    },
    {
      "label": "07/23 15:38",
      "value": 59.142
    },
    {
      "label": "07/23 15:42",
      "value": 59.079
    },
    {
      "label": "07/23 15:44",
      "value": 58.874
    },
    {
      "label": "07/23 15:46",
      "value": 58.93
    },
    {
      "label": "07/23 15:48",
      "value": 58.841
    },
    {
      "label": "07/23 15:52",
      "value": 58.956
    },
    {
      "label": "07/23 15:53",
      "value": 58.949
    },
    {
      "label": "07/23 15:54",
      "value": 58.951
    },
    {
      "label": "07/23 15:56",
      "value": 59.028
    },
    {
      "label": "07/23 15:58",
      "value": 59.075
    },
    {
      "label": "07/23 16:02",
      "value": 58.931
    },
    {
      "label": "07/23 16:04",
      "value": 59.035
    },
    {
      "label": "07/23 16:06",
      "value": 59.014
    },
    {
      "label": "07/23 16:08",
      "value": 59.013
    },
    {
      "label": "07/23 16:11",
      "value": 59.127
    },
    {
      "label": "07/23 16:12",
      "value": 59.054
    },
    {
      "label": "07/23 16:14",
      "value": 58.99
    },
    {
      "label": "07/23 16:16",
      "value": 58.962
    },
    {
      "label": "07/23 16:18",
      "value": 58.966
    },
    {
      "label": "07/23 16:21",
      "value": 58.969
    },
    {
      "label": "07/23 16:22",
      "value": 58.94
    },
    {
      "label": "07/23 16:24",
      "value": 58.946
    },
    {
      "label": "07/23 16:26",
      "value": 58.96
    },
    {
      "label": "07/23 16:28",
      "value": 58.999
    },
    {
      "label": "07/23 16:32",
      "value": 59.02
    },
    {
      "label": "07/23 16:34",
      "value": 59.013
    },
    {
      "label": "07/23 16:35",
      "value": 59.039
    },
    {
      "label": "07/23 16:36",
      "value": 58.983
    },
    {
      "label": "07/23 16:38",
      "value": 58.956
    },
    {
      "label": "07/23 16:40",
      "value": 58.938
    },
    {
      "label": "07/23 16:42",
      "value": 58.881
    },
    {
      "label": "07/23 16:44",
      "value": 58.889
    },
    {
      "label": "07/23 16:46",
      "value": 58.89
    },
    {
      "label": "07/23 16:48",
      "value": 58.868
    },
    {
      "label": "07/23 16:50",
      "value": 58.866
    },
    {
      "label": "07/23 16:52",
      "value": 58.889
    },
    {
      "label": "07/23 16:54",
      "value": 58.912
    },
    {
      "label": "07/23 16:56",
      "value": 58.983
    },
    {
      "label": "07/23 16:58",
      "value": 58.989
    },
    {
      "label": "07/23 17:02",
      "value": 59.03
    },
    {
      "label": "07/23 17:04",
      "value": 59.034
    },
    {
      "label": "07/23 17:06",
      "value": 59.108
    },
    {
      "label": "07/23 17:08",
      "value": 59.086
    },
    {
      "label": "07/23 17:12",
      "value": 59.082
    },
    {
      "label": "07/23 17:13",
      "value": 59.095
    },
    {
      "label": "07/23 17:14",
      "value": 59.079
    },
    {
      "label": "07/23 17:16",
      "value": 59.028
    },
    {
      "label": "07/23 17:18",
      "value": 59.07
    },
    {
      "label": "07/23 17:21",
      "value": 59.057
    },
    {
      "label": "07/23 17:22",
      "value": 58.991
    },
    {
      "label": "07/23 17:24",
      "value": 58.997
    },
    {
      "label": "07/23 17:26",
      "value": 58.961
    },
    {
      "label": "07/23 17:28",
      "value": 58.932
    },
    {
      "label": "07/23 17:32",
      "value": 58.953
    },
    {
      "label": "07/23 17:34",
      "value": 58.99
    },
    {
      "label": "07/23 17:36",
      "value": 58.993
    },
    {
      "label": "07/23 17:38",
      "value": 58.967
    },
    {
      "label": "07/23 17:42",
      "value": 58.989
    },
    {
      "label": "07/23 17:44",
      "value": 59.004
    },
    {
      "label": "07/23 17:46",
      "value": 58.987
    },
    {
      "label": "07/23 17:48",
      "value": 58.945
    },
    {
      "label": "07/23 17:50",
      "value": 58.965
    },
    {
      "label": "07/23 17:52",
      "value": 58.879
    },
    {
      "label": "07/23 17:54",
      "value": 58.933
    },
    {
      "label": "07/23 17:56",
      "value": 58.933
    },
    {
      "label": "07/23 17:58",
      "value": 58.87
    },
    {
      "label": "07/23 18:02",
      "value": 58.864
    },
    {
      "label": "07/23 18:04",
      "value": 58.842
    },
    {
      "label": "07/23 18:06",
      "value": 58.838
    }
  ],
  "source": "XAUS公开48小时白银现货分时",
  "refreshedAt": "2026-07-23T10:06:52.186Z"
}
