{
  "id": "wti",
  "range": "5D",
  "points": [
    {
      "label": "2026-07-06",
      "value": 69.6
    },
    {
      "label": "2026-07-07",
      "value": 71.53
    },
    {
      "label": "2026-07-08",
      "value": 74.56
    },
    {
      "label": "2026-07-09",
      "value": 73.15
    },
    {
      "label": "2026-07-10",
      "value": 72.45
    },
    {
      "label": "2026-07-13",
      "value": 79.2
    }
  ],
  "source": "FRED公开日频商品价格",
  "refreshedAt": "2026-07-21T06:18:33.273Z"
}
